<?xml version="1.0"?>
<?xml-stylesheet type="text/xsl" href="configuration.xsl"?>
<configuration>

    <property>
        <name>javax.jdo.option.ConnectionURL</name>
        <value>jdbc:mysql://localhost:3306/metastore
            ?createDatabaseIfNotExist=true
        </value>
        <description>JDBC connect string for a JDBC metastore</description>
    </property>

    <property>
        <name>datanucleus.schema.autoCreateAll</name>
        <value>true</value>
        <description>
            creates necessary schema on a startup if one doesn't exist.
        </description>
    </property>

    <property>
        <name>javax.jdo.option.ConnectionDriverName</name>
        <value>com.mysql.jdbc.Driver</value>
        <description>Driver class name for a JDBC metastore</description>
    </property>

    <property>
        <name>javax.jdo.option.ConnectionUserName</name>
        <value>root</value>
        <description>username to use against metastore database</description>
    </property>

    <property>
        <name>javax.jdo.option.ConnectionPassword</name>
        <value/>
        <description>password to use against metastore database</description>
    </property>

    <property>
        <name>hive.metastore.uris</name>
        <value>thrift://localhost:9083</value>
    </property>

    <property>
        <name>hive.zookeeper.client.port</name>
        <value>5181</value>
    </property>

    <property>
        <name>hbase.zookeeper.property.clientPort</name>
        <value>5181</value>
    </property>

    <property>
        <name>hive.metastore.execute.setugi</name>
        <value>true</value>
    </property>

</configuration>
